utdate/.DS_Store
utdate/__init__.py
utdate/__main__.py
utdate/bin/.DS_Store
utdate/bin/Commands.txt
utdate/bin/__init__.py
utdate/bin/abc.history
utdate/bin/abc.rc
utdate/bin/abc_script.scr
utdate/bin/mycells.v
utdate/bin/pthreadVC2.dll
utdate/bin/__pycache__/__init__.cpython-310.pyc
utdate/bin/darwin/.DS_Store
utdate/bin/darwin/bin/yosys
utdate/bin/darwin/bin/yosys-abc
utdate/bin/darwin/bin/yosys-config
utdate/bin/darwin/bin/yosys-smtbmc
utdate/bin/win/.DS_Store
utdate/bin/win/bin/.DS_Store
utdate/bin/win/bin/Commands.txt
utdate/bin/win/bin/abc.history
utdate/bin/win/bin/abc.rc
utdate/bin/win/bin/abc_script.scr
utdate/bin/win/bin/libffi-6.dll
utdate/bin/win/bin/libgcc_s_seh-1.dll
utdate/bin/win/bin/libpython3.8.dll
utdate/bin/win/bin/libreadline8.dll
utdate/bin/win/bin/libssl-1_1-x64.dll
utdate/bin/win/bin/libssp-0.dll
utdate/bin/win/bin/libstdc++-6.dll
utdate/bin/win/bin/libtermcap-0.dll
utdate/bin/win/bin/libtextstyle-0.dll
utdate/bin/win/bin/libtiffxx-5.dll
utdate/bin/win/bin/libwinpthread-1.dll
utdate/bin/win/bin/libxml2-2.dll
utdate/bin/win/bin/libyices.dll
utdate/bin/win/bin/mycells.lib
utdate/bin/win/bin/mycells.v
utdate/bin/win/bin/pthreadVC2.dll
utdate/bin/win/bin/tcl86.dll
utdate/bin/win/bin/tk86.dll
utdate/bin/win/bin/yosys-abc.exe
utdate/bin/win/bin/yosys-config
utdate/bin/win/bin/yosys-filterlib.exe
utdate/bin/win/bin/yosys-smtbmc-script.py
utdate/bin/win/bin/yosys-smtbmc.exe
utdate/bin/win/bin/yosys-witness-script.py
utdate/bin/win/bin/yosys-witness.exe
utdate/bin/win/bin/yosys.exe
utdate/bin/win/bin/z3.exe
utdate/bin/win/bin/zlib1.dll
utdate/bin/win/share/.DS_Store
utdate/bin/win/share/yosys/.DS_Store
utdate/bin/win/share/yosys/abc9_map.v
utdate/bin/win/share/yosys/abc9_model.v
utdate/bin/win/share/yosys/abc9_unmap.v
utdate/bin/win/share/yosys/adff2dff.v
utdate/bin/win/share/yosys/cells.lib
utdate/bin/win/share/yosys/cmp2lcu.v
utdate/bin/win/share/yosys/cmp2lut.v
utdate/bin/win/share/yosys/dff2ff.v
utdate/bin/win/share/yosys/gate2lut.v
ut_date-1.5.0.dist-info/LICENSE
ut_date-1.5.0.dist-info/METADATA
ut_date-1.5.0.dist-info/WHEEL
ut_date-1.5.0.dist-info/top_level.txt
ut_date-1.5.0.dist-info/RECORD
