Metadata-Version: 2.1
Name: ut-date
Version: 1.5.0
Summary: Design And Test Environment
Home-page: https://github.com/UTehran-NavabiLab/NBGen
Author: Navabi Lab Group
Author-email: nouri.ebrahim@ut.ac.ir
Project-URL: Bug Tracker, https://github.com/UTehran-NavabiLab/NBGen/issues
Classifier: Programming Language :: Python :: 3
Classifier: License :: OSI Approved :: MIT License
Classifier: Operating System :: OS Independent
Requires-Python: >=3.6
License-File: LICENSE
Requires-Dist: liberty-parser
